README.md
nautobot_chatops_ansible/__init__.py
nautobot_chatops_ansible/static/nautobot_ansible/Ansible_Logo.png
nautobot_chatops_ansible/tests/__init__.py
nautobot_chatops_ansible/tests/fixtures/01_get_inventories.json
nautobot_chatops_ansible/tests/fixtures/02_get_inventory_groups.json
nautobot_chatops_ansible/tests/fixtures/03_get_inventory_hosts.json
nautobot_chatops_ansible/tests/fixtures/04_get_dashboard.json
nautobot_chatops_ansible/tests/fixtures/05_get_jobs.json
nautobot_chatops_ansible/tests/fixtures/06_get_projects.json
nautobot_chatops_ansible/tests/test_tower.py
nautobot_chatops_ansible/tower.py
nautobot_chatops_ansible/worker.py
nautobot_chatops_ansible-1.0.3.dist-info/entry_points.txt
nautobot_chatops_ansible-1.0.3.dist-info/WHEEL
nautobot_chatops_ansible-1.0.3.dist-info/METADATA
nautobot_chatops_ansible-1.0.3.dist-info/RECORD
