Metadata-Version: 2.1
Name: nautobot-chatops-ansible
Version: 1.0.3
Summary: Nautobot Chatpops Ansible Tower integration
Home-page: https://github.com/nautobot/nautobot-plugin-chatops-ansible
Keywords: nautobot,nautobot-plugin
Author: Network to Code, LLC
Author-email: opensource@networktocode.com
Requires-Python: >=3.6,<4.0
Classifier: Programming Language :: Python :: 3
Classifier: Programming Language :: Python :: 3.6
Classifier: Programming Language :: Python :: 3.7
Classifier: Programming Language :: Python :: 3.8
Classifier: Programming Language :: Python :: 3.9
Requires-Dist: nautobot-chatops (>=1.1.0,<2.0.0)
Requires-Dist: requests (>=2.25.1,<3.0.0)
Project-URL: Repository, https://github.com/nautobot/nautobot-plugin-chatops-ansible
